NiukeYouxiKaifaGongchengshiQiuzhiJingyanFenxiang20212022Fix1/README.md
NiukeYouxiKaifaGongchengshiQiuzhiJingyanFenxiang20212022Fix1/__init__.py
NiukeYouxiKaifaGongchengshiQiuzhiJingyanFenxiang20212022Fix1/__main__.py
NiukeYouxiKaifaGongchengshiQiuzhiJingyanFenxiang20212022Fix1/file.epub
NiukeYouxiKaifaGongchengshiQiuzhiJingyanFenxiang20212022Fix1/index.html
NiukeYouxiKaifaGongchengshiQiuzhiJingyanFenxiang20212022Fix1/css/__init__.py
NiukeYouxiKaifaGongchengshiQiuzhiJingyanFenxiang20212022Fix1/css/annotations.css
NiukeYouxiKaifaGongchengshiQiuzhiJingyanFenxiang20212022Fix1/css/main.css
NiukeYouxiKaifaGongchengshiQiuzhiJingyanFenxiang20212022Fix1/css/normalize.css
NiukeYouxiKaifaGongchengshiQiuzhiJingyanFenxiang20212022Fix1/css/popup.css
NiukeYouxiKaifaGongchengshiQiuzhiJingyanFenxiang20212022Fix1/font/__init__.py
NiukeYouxiKaifaGongchengshiQiuzhiJingyanFenxiang20212022Fix1/font/fontello.eot
NiukeYouxiKaifaGongchengshiQiuzhiJingyanFenxiang20212022Fix1/font/fontello.svg
NiukeYouxiKaifaGongchengshiQiuzhiJingyanFenxiang20212022Fix1/font/fontello.ttf
NiukeYouxiKaifaGongchengshiQiuzhiJingyanFenxiang20212022Fix1/font/fontello.woff
NiukeYouxiKaifaGongchengshiQiuzhiJingyanFenxiang20212022Fix1/img/__init__.py
NiukeYouxiKaifaGongchengshiQiuzhiJingyanFenxiang20212022Fix1/img/annotator-glyph-sprite.png
NiukeYouxiKaifaGongchengshiQiuzhiJingyanFenxiang20212022Fix1/img/annotator-icon-sprite.png
NiukeYouxiKaifaGongchengshiQiuzhiJingyanFenxiang20212022Fix1/img/apple-touch-icon.png
NiukeYouxiKaifaGongchengshiQiuzhiJingyanFenxiang20212022Fix1/img/cancelfullscreen.png
NiukeYouxiKaifaGongchengshiQiuzhiJingyanFenxiang20212022Fix1/img/close.png
NiukeYouxiKaifaGongchengshiQiuzhiJingyanFenxiang20212022Fix1/img/fullscreen.png
NiukeYouxiKaifaGongchengshiQiuzhiJingyanFenxiang20212022Fix1/img/loader.gif
NiukeYouxiKaifaGongchengshiQiuzhiJingyanFenxiang20212022Fix1/img/menu-icon.png
NiukeYouxiKaifaGongchengshiQiuzhiJingyanFenxiang20212022Fix1/img/save.png
niuke_youxi_kaifa_gongchengshi_qiuzhi_jingyan_fenxiang_2021_2022_fix1-2025.3.25.1.dist-info/METADATA
niuke_youxi_kaifa_gongchengshi_qiuzhi_jingyan_fenxiang_2021_2022_fix1-2025.3.25.1.dist-info/WHEEL
niuke_youxi_kaifa_gongchengshi_qiuzhi_jingyan_fenxiang_2021_2022_fix1-2025.3.25.1.dist-info/entry_points.txt
niuke_youxi_kaifa_gongchengshi_qiuzhi_jingyan_fenxiang_2021_2022_fix1-2025.3.25.1.dist-info/top_level.txt
niuke_youxi_kaifa_gongchengshi_qiuzhi_jingyan_fenxiang_2021_2022_fix1-2025.3.25.1.dist-info/RECORD
